{
    "129103": {
        "subtree": {
            "129206": {
                "sourceCellId": 129103,
                "effectValue": 74,
                "enhancementType": "ATTACK"
            },
            "129511": {
                "sourceCellId": 129512,
                "effectValue": 86,
                "enhancementType": "ATTACK"
            },
            "129512": {
                "sourceCellId": 129513,
                "effectValue": 140,
                "enhancementType": "DEFENSE"
            },
            "129513": {
                "sourceCellId": 129410,
                "effectValue": 342,
                "enhancementType": "HP"
            },
            "129410": {
                "sourceCellId": 129411,
                "effectValue": 323,
                "enhancementType": "HP"
            },
            "129411": {
                "sourceCellId": 129308,
                "effectValue": 133,
                "enhancementType": "DEFENSE"
            },
            "129308": {
                "sourceCellId": 129206,
                "effectValue": 125,
                "enhancementType": "DEFENSE"
            }
        },
        "targets": [
            129206,
            129511
        ]
    },
    "129102": {
        "subtree": {
            "129304": {
                "sourceCellId": 129203,
                "effectValue": 78,
                "enhancementType": "ATTACK"
            },
            "129203": {
                "sourceCellId": 129102,
                "effectValue": 289,
                "enhancementType": "HP"
            },
            "129504": {
                "sourceCellId": 129403,
                "effectValue": 86,
                "enhancementType": "ATTACK"
            },
            "129403": {
                "sourceCellId": 129303,
                "effectValue": 323,
                "enhancementType": "HP"
            },
            "129303": {
                "sourceCellId": 129202,
                "effectValue": 305,
                "enhancementType": "HP"
            },
            "129202": {
                "sourceCellId": 129102,
                "effectValue": 289,
                "enhancementType": "HP"
            },
            "129505": {
                "sourceCellId": 129404,
                "effectValue": 86,
                "enhancementType": "ATTACK"
            },
            "129404": {
                "sourceCellId": 129303,
                "effectValue": 323,
                "enhancementType": "HP"
            }
        },
        "targets": [
            129304,
            129504,
            129505
        ]
    },
    "129201": {
        "subtree": {
            "129318": {
                "sourceCellId": 129201,
                "effectValue": 78,
                "enhancementType": "ATTACK"
            },
            "129402": {
                "sourceCellId": 129302,
                "effectValue": 81,
                "enhancementType": "ATTACK"
            },
            "129302": {
                "sourceCellId": 129201,
                "effectValue": 305,
                "enhancementType": "HP"
            },
            "129501": {
                "sourceCellId": 129530,
                "effectValue": 86,
                "enhancementType": "ATTACK"
            },
            "129530": {
                "sourceCellId": 129529,
                "effectValue": 125,
                "enhancementType": "ATTACK"
            },
            "129529": {
                "sourceCellId": 129424,
                "effectValue": 140,
                "enhancementType": "DEFENSE"
            },
            "129424": {
                "sourceCellId": 129318,
                "effectValue": 133,
                "enhancementType": "DEFENSE"
            },
            "129503": {
                "sourceCellId": 129402,
                "effectValue": 86,
                "enhancementType": "ATTACK"
            }
        },
        "targets": [
            129318,
            129402,
            129501,
            129530,
            129503
        ]
    },
    "129301": {
        "subtree": {
            "129401": {
                "sourceCellId": 129301,
                "effectValue": 81,
                "enhancementType": "ATTACK"
            }
        },
        "targets": [
            129401
        ]
    },
    "129314": {
        "subtree": {
            "129420": {
                "sourceCellId": 129315,
                "effectValue": 81,
                "enhancementType": "ATTACK"
            },
            "129315": {
                "sourceCellId": 129314,
                "effectValue": 125,
                "enhancementType": "DEFENSE"
            }
        },
        "targets": [
            129420
        ]
    },
    "129422": {
        "subtree": {
            "129421": {
                "sourceCellId": 129422,
                "effectValue": 81,
                "enhancementType": "ATTACK"
            }
        },
        "targets": [
            129421
        ]
    },
    "129306": {
        "subtree": {
            "129510": {
                "sourceCellId": 129408,
                "effectValue": 86,
                "enhancementType": "ATTACK"
            },
            "129408": {
                "sourceCellId": 129306,
                "effectValue": 323,
                "enhancementType": "HP"
            },
            "129603": {
                "sourceCellId": 129604,
                "effectValue": 86,
                "enhancementType": "ATTACK"
            },
            "129604": {
                "sourceCellId": 129510,
                "effectValue": 140,
                "enhancementType": "DEFENSE"
            }
        },
        "targets": [
            129510,
            129603
        ]
    },
    "129207": {
        "subtree": {
            "129514": {
                "sourceCellId": 129515,
                "effectValue": 125,
                "enhancementType": "ATTACK"
            },
            "129515": {
                "sourceCellId": 129516,
                "effectValue": 140,
                "enhancementType": "DEFENSE"
            },
            "129516": {
                "sourceCellId": 129413,
                "effectValue": 469,
                "enhancementType": "HP"
            },
            "129413": {
                "sourceCellId": 129310,
                "effectValue": 133,
                "enhancementType": "DEFENSE"
            },
            "129310": {
                "sourceCellId": 129207,
                "effectValue": 125,
                "enhancementType": "DEFENSE"
            },
            "129517": {
                "sourceCellId": 129414,
                "effectValue": 86,
                "enhancementType": "ATTACK"
            },
            "129414": {
                "sourceCellId": 129311,
                "effectValue": 133,
                "enhancementType": "DEFENSE"
            },
            "129311": {
                "sourceCellId": 129207,
                "effectValue": 305,
                "enhancementType": "HP"
            }
        },
        "targets": [
            129514,
            129517
        ]
    },
    "129312": {
        "subtree": {
            "129519": {
                "sourceCellId": 129415,
                "effectValue": 86,
                "enhancementType": "ATTACK"
            },
            "129415": {
                "sourceCellId": 129312,
                "effectValue": 133,
                "enhancementType": "DEFENSE"
            }
        },
        "targets": [
            129519
        ]
    },
    "129416": {
        "subtree": {
            "129521": {
                "sourceCellId": 129417,
                "effectValue": 125,
                "enhancementType": "ATTACK"
            },
            "129417": {
                "sourceCellId": 129416,
                "effectValue": 323,
                "enhancementType": "HP"
            },
            "129606": {
                "sourceCellId": 129521,
                "effectValue": 86,
                "enhancementType": "ATTACK"
            }
        },
        "targets": [
            129521,
            129606
        ]
    },
    "129407": {
        "subtree": {
            "129602": {
                "sourceCellId": 129507,
                "effectValue": 125,
                "enhancementType": "ATTACK"
            },
            "129507": {
                "sourceCellId": 129406,
                "effectValue": 342,
                "enhancementType": "HP"
            },
            "129406": {
                "sourceCellId": 129407,
                "effectValue": 323,
                "enhancementType": "HP"
            }
        },
        "targets": [
            129602
        ]
    }
}