[
    {
        "1": {
            "bonus": {
                "ATTACK": 81,
                "DEFENSE": 0,
                "HP": 0
            },
            "path": [
                172201,
                172202
            ],
            "eff": 81
        },
        "3": {
            "bonus": {
                "ATTACK": 172,
                "DEFENSE": 88,
                "HP": 0
            },
            "path": [
                172201,
                172202,
                172404,
                172303
            ],
            "eff": 57.333333333333336
        },
        "4": {
            "bonus": {
                "ATTACK": 267,
                "DEFENSE": 88,
                "HP": 0
            },
            "path": [
                172201,
                172202,
                172404,
                172303,
                172504
            ],
            "eff": 66.75
        },
        "5": {
            "bonus": {
                "ATTACK": 362,
                "DEFENSE": 88,
                "HP": 0
            },
            "path": [
                172201,
                172202,
                172404,
                172303,
                172503,
                172504
            ],
            "eff": 72.4
        },
        "6": {
            "bonus": {
                "ATTACK": 362,
                "DEFENSE": 88,
                "HP": 229
            },
            "path": [
                172201,
                172202,
                172302,
                172404,
                172303,
                172503,
                172504
            ],
            "eff": 60.333333333333336
        },
        "7": {
            "bonus": {
                "ATTACK": 362,
                "DEFENSE": 88,
                "HP": 471
            },
            "path": [
                172201,
                172202,
                172403,
                172302,
                172404,
                172303,
                172503,
                172504
            ],
            "eff": 51.714285714285715
        },
        "8": {
            "bonus": {
                "ATTACK": 453,
                "DEFENSE": 88,
                "HP": 471
            },
            "path": [
                172201,
                172202,
                172402,
                172403,
                172302,
                172404,
                172303,
                172502,
                172504
            ],
            "eff": 56.625
        },
        "9": {
            "bonus": {
                "ATTACK": 548,
                "DEFENSE": 88,
                "HP": 471
            },
            "path": [
                172201,
                172202,
                172402,
                172403,
                172302,
                172404,
                172303,
                172502,
                172503,
                172504
            ],
            "eff": 60.888888888888886
        }
    },
    {
        "1": {
            "bonus": {
                "ATTACK": 87,
                "DEFENSE": 0,
                "HP": 0
            },
            "path": [
                172203,
                172304
            ],
            "eff": 87
        },
        "3": {
            "bonus": {
                "ATTACK": 182,
                "DEFENSE": 0,
                "HP": 242
            },
            "path": [
                172203,
                172304,
                172506,
                172405
            ],
            "eff": 60.666666666666664
        },
        "4": {
            "bonus": {
                "ATTACK": 277,
                "DEFENSE": 0,
                "HP": 242
            },
            "path": [
                172203,
                172304,
                172505,
                172506,
                172405
            ],
            "eff": 69.25
        }
    },
    {
        "1": {
            "bonus": {
                "ATTACK": 87,
                "DEFENSE": 0,
                "HP": 0
            },
            "path": [
                172212,
                172317
            ],
            "eff": 87
        },
        "4": {
            "bonus": {
                "ATTACK": 226,
                "DEFENSE": 0,
                "HP": 593
            },
            "path": [
                172212,
                172317,
                172529,
                172528,
                172422
            ],
            "eff": 56.5
        }
    },
    {
        "1": {
            "bonus": {
                "ATTACK": 91,
                "DEFENSE": 0,
                "HP": 0
            },
            "path": [
                172306,
                172407
            ],
            "eff": 91
        },
        "5": {
            "bonus": {
                "ATTACK": 230,
                "DEFENSE": 233,
                "HP": 256
            },
            "path": [
                172306,
                172407,
                172604,
                172603,
                172602,
                172508
            ],
            "eff": 46
        }
    },
    {
        "1": {
            "bonus": {
                "ATTACK": 91,
                "DEFENSE": 0,
                "HP": 0
            },
            "path": [
                172315,
                172420
            ],
            "eff": 91
        }
    },
    {
        "1": {
            "bonus": {
                "ATTACK": 91,
                "DEFENSE": 0,
                "HP": 0
            },
            "path": [
                172423,
                172424
            ],
            "eff": 91
        },
        "3": {
            "bonus": {
                "ATTACK": 186,
                "DEFENSE": 0,
                "HP": 256
            },
            "path": [
                172423,
                172424,
                172501,
                172530
            ],
            "eff": 62
        }
    },
    {
        "4": {
            "bonus": {
                "ATTACK": 95,
                "DEFENSE": 192,
                "HP": 256
            },
            "path": [
                172307,
                172511,
                172510,
                172509,
                172408
            ],
            "eff": 23.75
        }
    },
    {
        "2": {
            "bonus": {
                "ATTACK": 95,
                "DEFENSE": 94,
                "HP": 0
            },
            "path": [
                172409,
                172513,
                172410
            ],
            "eff": 47.5
        }
    },
    {
        "2": {
            "bonus": {
                "ATTACK": 95,
                "DEFENSE": 0,
                "HP": 256
            },
            "path": [
                172415,
                172518,
                172519
            ],
            "eff": 47.5
        }
    },
    {
        "2": {
            "bonus": {
                "ATTACK": 95,
                "DEFENSE": 0,
                "HP": 242
            },
            "path": [
                172316,
                172526,
                172421
            ],
            "eff": 47.5
        },
        "3": {
            "bonus": {
                "ATTACK": 234,
                "DEFENSE": 0,
                "HP": 242
            },
            "path": [
                172316,
                172526,
                172421,
                172527
            ],
            "eff": 78
        }
    },
    {
        "1": {
            "bonus": {
                "ATTACK": 139,
                "DEFENSE": 0,
                "HP": 0
            },
            "path": [
                172524,
                172609
            ],
            "eff": 139
        }
    }
]