[
    {
        "1": {
            "bonus": {
                "ATTACK": 74,
                "DEFENSE": 0,
                "HP": 0
            },
            "path": [
                74208,
                74312
            ],
            "eff": 74
        },
        "3": {
            "bonus": {
                "ATTACK": 153,
                "DEFENSE": 93,
                "HP": 0
            },
            "path": [
                74208,
                74312,
                74417,
                74416
            ],
            "eff": 51
        },
        "4": {
            "bonus": {
                "ATTACK": 237,
                "DEFENSE": 93,
                "HP": 0
            },
            "path": [
                74208,
                74312,
                74417,
                74416,
                74522
            ],
            "eff": 59.25
        },
        "5": {
            "bonus": {
                "ATTACK": 279,
                "DEFENSE": 0,
                "HP": 414
            },
            "path": [
                74208,
                74312,
                74523,
                74418,
                74313,
                74524
            ],
            "eff": 55.8
        },
        "6": {
            "bonus": {
                "ATTACK": 321,
                "DEFENSE": 93,
                "HP": 227
            },
            "path": [
                74208,
                74312,
                74417,
                74416,
                74522,
                74608,
                74607
            ],
            "eff": 53.5
        },
        "7": {
            "bonus": {
                "ATTACK": 358,
                "DEFENSE": 93,
                "HP": 414
            },
            "path": [
                74208,
                74312,
                74417,
                74416,
                74523,
                74418,
                74313,
                74524
            ],
            "eff": 51.142857142857146
        },
        "8": {
            "bonus": {
                "ATTACK": 442,
                "DEFENSE": 191,
                "HP": 227
            },
            "path": [
                74208,
                74312,
                74417,
                74416,
                74522,
                74608,
                74607,
                74610,
                74609
            ],
            "eff": 55.25
        },
        "9": {
            "bonus": {
                "ATTACK": 442,
                "DEFENSE": 191,
                "HP": 428
            },
            "path": [
                74208,
                74312,
                74417,
                74416,
                74522,
                74313,
                74608,
                74607,
                74610,
                74609
            ],
            "eff": 49.111111111111114
        },
        "10": {
            "bonus": {
                "ATTACK": 526,
                "DEFENSE": 93,
                "HP": 641
            },
            "path": [
                74208,
                74312,
                74417,
                74416,
                74522,
                74523,
                74418,
                74313,
                74524,
                74608,
                74607
            ],
            "eff": 52.6
        },
        "11": {
            "bonus": {
                "ATTACK": 526,
                "DEFENSE": 191,
                "HP": 641
            },
            "path": [
                74208,
                74312,
                74417,
                74416,
                74522,
                74523,
                74418,
                74313,
                74608,
                74607,
                74610,
                74609
            ],
            "eff": 47.81818181818182
        },
        "12": {
            "bonus": {
                "ATTACK": 647,
                "DEFENSE": 191,
                "HP": 641
            },
            "path": [
                74208,
                74312,
                74417,
                74416,
                74522,
                74523,
                74418,
                74313,
                74524,
                74608,
                74607,
                74610,
                74609
            ],
            "eff": 53.916666666666664
        }
    },
    {
        "2": {
            "bonus": {
                "ATTACK": 79,
                "DEFENSE": 93,
                "HP": 0
            },
            "path": [
                74402,
                74404,
                74403
            ],
            "eff": 39.5
        },
        "4": {
            "bonus": {
                "ATTACK": 163,
                "DEFENSE": 191,
                "HP": 0
            },
            "path": [
                74402,
                74404,
                74403,
                74506,
                74505
            ],
            "eff": 40.75
        }
    },
    {
        "2": {
            "bonus": {
                "ATTACK": 79,
                "DEFENSE": 0,
                "HP": 213
            },
            "path": [
                74310,
                74414,
                74413
            ],
            "eff": 39.5
        }
    },
    {
        "2": {
            "bonus": {
                "ATTACK": 79,
                "DEFENSE": 0,
                "HP": 213
            },
            "path": [
                74317,
                74423,
                74422
            ],
            "eff": 39.5
        },
        "4": {
            "bonus": {
                "ATTACK": 163,
                "DEFENSE": 93,
                "HP": 213
            },
            "path": [
                74317,
                74423,
                74422,
                74530,
                74424
            ],
            "eff": 40.75
        },
        "5": {
            "bonus": {
                "ATTACK": 284,
                "DEFENSE": 93,
                "HP": 213
            },
            "path": [
                74317,
                74423,
                74422,
                74501,
                74530,
                74424
            ],
            "eff": 56.8
        }
    },
    {
        "5": {
            "bonus": {
                "ATTACK": 84,
                "DEFENSE": 191,
                "HP": 454
            },
            "path": [
                74305,
                74511,
                74510,
                74509,
                74508,
                74406
            ],
            "eff": 16.8
        }
    },
    {
        "2": {
            "bonus": {
                "ATTACK": 84,
                "DEFENSE": 0,
                "HP": 227
            },
            "path": [
                74415,
                74520,
                74519
            ],
            "eff": 42
        },
        "4": {
            "bonus": {
                "ATTACK": 205,
                "DEFENSE": 98,
                "HP": 227
            },
            "path": [
                74415,
                74520,
                74519,
                74606,
                74521
            ],
            "eff": 51.25
        }
    },
    {
        "2": {
            "bonus": {
                "ATTACK": 84,
                "DEFENSE": 0,
                "HP": 227
            },
            "path": [
                74526,
                74528,
                74527
            ],
            "eff": 42
        },
        "3": {
            "bonus": {
                "ATTACK": 168,
                "DEFENSE": 0,
                "HP": 227
            },
            "path": [
                74526,
                74528,
                74527,
                74529
            ],
            "eff": 56
        }
    },
    {
        "2": {
            "bonus": {
                "ATTACK": 84,
                "DEFENSE": 98,
                "HP": 0
            },
            "path": [
                74405,
                74602,
                74507
            ],
            "eff": 42
        }
    }
]