[
    {
        "1": {
            "bonus": {
                "ATTACK": 48,
                "DEFENSE": 0,
                "HP": 0
            },
            "path": [
                36206,
                36308
            ],
            "eff": 48
        },
        "5": {
            "bonus": {
                "ATTACK": 144,
                "DEFENSE": 98,
                "HP": 246
            },
            "path": [
                36206,
                36308,
                36516,
                36413,
                36412,
                36309
            ],
            "eff": 28.8
        }
    },
    {
        "3": {
            "bonus": {
                "ATTACK": 50,
                "DEFENSE": 93,
                "HP": 116
            },
            "path": [
                36101,
                36403,
                36302,
                36202
            ],
            "eff": 16.666666666666668
        }
    },
    {
        "1": {
            "bonus": {
                "ATTACK": 50,
                "DEFENSE": 0,
                "HP": 0
            },
            "path": [
                36306,
                36408
            ],
            "eff": 50
        }
    },
    {
        "1": {
            "bonus": {
                "ATTACK": 50,
                "DEFENSE": 0,
                "HP": 0
            },
            "path": [
                36316,
                36420
            ],
            "eff": 50
        },
        "3": {
            "bonus": {
                "ATTACK": 103,
                "DEFENSE": 111,
                "HP": 0
            },
            "path": [
                36316,
                36420,
                36526,
                36525
            ],
            "eff": 34.333333333333336
        }
    },
    {
        "2": {
            "bonus": {
                "ATTACK": 53,
                "DEFENSE": 105,
                "HP": 0
            },
            "path": [
                36304,
                36505,
                36404
            ],
            "eff": 26.5
        },
        "4": {
            "bonus": {
                "ATTACK": 106,
                "DEFENSE": 216,
                "HP": 0
            },
            "path": [
                36304,
                36505,
                36404,
                36601,
                36506
            ],
            "eff": 26.5
        }
    },
    {
        "3": {
            "bonus": {
                "ATTACK": 53,
                "DEFENSE": 216,
                "HP": 0
            },
            "path": [
                36410,
                36515,
                36514,
                36411
            ],
            "eff": 17.666666666666668
        }
    },
    {
        "3": {
            "bonus": {
                "ATTACK": 96,
                "DEFENSE": 0,
                "HP": 251
            },
            "path": [
                36310,
                36518,
                36517,
                36414
            ],
            "eff": 32
        }
    },
    {
        "3": {
            "bonus": {
                "ATTACK": 53,
                "DEFENSE": 0,
                "HP": 251
            },
            "path": [
                36311,
                36520,
                36519,
                36415
            ],
            "eff": 17.666666666666668
        }
    },
    {
        "3": {
            "bonus": {
                "ATTACK": 53,
                "DEFENSE": 0,
                "HP": 251
            },
            "path": [
                36314,
                36523,
                36522,
                36418
            ],
            "eff": 17.666666666666668
        }
    },
    {
        "3": {
            "bonus": {
                "ATTACK": 53,
                "DEFENSE": 98,
                "HP": 123
            },
            "path": [
                36210,
                36524,
                36419,
                36315
            ],
            "eff": 17.666666666666668
        },
        "5": {
            "bonus": {
                "ATTACK": 149,
                "DEFENSE": 98,
                "HP": 251
            },
            "path": [
                36210,
                36524,
                36419,
                36315,
                36610,
                36609
            ],
            "eff": 29.8
        }
    },
    {
        "2": {
            "bonus": {
                "ATTACK": 53,
                "DEFENSE": 0,
                "HP": 128
            },
            "path": [
                36423,
                36530,
                36529
            ],
            "eff": 26.5
        }
    },
    {
        "3": {
            "bonus": {
                "ATTACK": 53,
                "DEFENSE": 111,
                "HP": 128
            },
            "path": [
                36407,
                36604,
                36603,
                36509
            ],
            "eff": 17.666666666666668
        }
    },
    {
        "2": {
            "bonus": {
                "ATTACK": 53,
                "DEFENSE": 0,
                "HP": 128
            },
            "path": [
                36417,
                36606,
                36521
            ],
            "eff": 26.5
        },
        "4": {
            "bonus": {
                "ATTACK": 149,
                "DEFENSE": 111,
                "HP": 128
            },
            "path": [
                36417,
                36606,
                36521,
                36608,
                36607
            ],
            "eff": 37.25
        }
    }
]